adamapi/__init__.py
adamapi/authorization.py
adamapi/datasets.py
adamapi/get_data.py
adamapi/search.py
eo4eu_adamapi-2.3.0.dist-info/METADATA
eo4eu_adamapi-2.3.0.dist-info/WHEEL
eo4eu_adamapi-2.3.0.dist-info/top_level.txt
eo4eu_adamapi-2.3.0.dist-info/RECORD
